clevercsv-0.8.3.data/data/man/man1/clevercsv.1
clevercsv-0.8.3.data/data/man/man1/clevercsv-explore.1
clevercsv-0.8.3.data/data/man/man1/clevercsv-help.1
clevercsv-0.8.3.data/data/man/man1/clevercsv-detect.1
clevercsv-0.8.3.data/data/man/man1/clevercsv-standardize.1
clevercsv-0.8.3.data/data/man/man1/clevercsv-code.1
clevercsv-0.8.3.data/data/man/man1/clevercsv-view.1
clevercsv/write.py
clevercsv/cabstraction.pyi
clevercsv/cparser_util.py
clevercsv/utils.py
clevercsv/cparser.pyi
clevercsv/__version__.py
clevercsv/detect_pattern.py
clevercsv/wrappers.py
clevercsv/break_ties.py
clevercsv/detect.py
clevercsv/cabstraction.cpython-38-x86_64-linux-gnu.so
clevercsv/cparser_util.pyi
clevercsv/_optional.py
clevercsv/exceptions.py
clevercsv/__init__.py
clevercsv/consistency.py
clevercsv/potential_dialects.py
clevercsv/dialect.py
clevercsv/escape.py
clevercsv/_types.py
clevercsv/cparser.cpython-38-x86_64-linux-gnu.so
clevercsv/read.py
clevercsv/__main__.py
clevercsv/encoding.py
clevercsv/normal_form.py
clevercsv/dict_read_write.py
clevercsv/detect_type.py
clevercsv/_regexes.py
clevercsv/py.typed
clevercsv/console/application.py
clevercsv/console/__init__.py
clevercsv/console/commands/standardize.py
clevercsv/console/commands/_utils.py
clevercsv/console/commands/detect.py
clevercsv/console/commands/__init__.py
clevercsv/console/commands/explore.py
clevercsv/console/commands/_docs.py
clevercsv/console/commands/code.py
clevercsv/console/commands/view.py
clevercsv-0.8.3.dist-info/top_level.txt
clevercsv-0.8.3.dist-info/RECORD
clevercsv-0.8.3.dist-info/LICENSE
clevercsv-0.8.3.dist-info/entry_points.txt
clevercsv-0.8.3.dist-info/METADATA
clevercsv-0.8.3.dist-info/WHEEL
