Metadata-Version: 2.1
Name: clevercsv
Version: 0.8.3
Summary: A Python package for handling messy CSV files
Home-page: https://github.com/alan-turing-institute/CleverCSV
Author: Gertjan van den Burg
Author-email: gertjanvandenburg@gmail.com
License: MIT
Classifier: License :: OSI Approved :: MIT License
Classifier: Programming Language :: Python
Classifier: Programming Language :: Python :: 3
Classifier: Programming Language :: Python :: 3.6
Classifier: Programming Language :: Python :: Implementation :: CPython
Classifier: Programming Language :: Python :: Implementation :: PyPy
Requires-Python: >=3.8.0
License-File: LICENSE
Requires-Dist: chardet >=3.0
Requires-Dist: regex >=2018.11
Requires-Dist: packaging >=23.0
Provides-Extra: dev
Requires-Dist: sphinx ; extra == 'dev'
Requires-Dist: m2r2 ; extra == 'dev'
Requires-Dist: furo ; extra == 'dev'
Requires-Dist: wilderness >=0.1.5 ; extra == 'dev'
Requires-Dist: faust-cchardet >=2.1.18 ; extra == 'dev'
Requires-Dist: pandas >=1.0.0 ; extra == 'dev'
Requires-Dist: tabview >=1.4 ; extra == 'dev'
Requires-Dist: green ; extra == 'dev'
Requires-Dist: pytest >=2.6 ; extra == 'dev'
Requires-Dist: termcolor ; extra == 'dev'
Requires-Dist: mypy ; extra == 'dev'
Provides-Extra: docs
Requires-Dist: sphinx ; extra == 'docs'
Requires-Dist: m2r2 ; extra == 'docs'
Requires-Dist: furo ; extra == 'docs'
Provides-Extra: full
Requires-Dist: wilderness >=0.1.5 ; extra == 'full'
Requires-Dist: faust-cchardet >=2.1.18 ; extra == 'full'
Requires-Dist: pandas >=1.0.0 ; extra == 'full'
Requires-Dist: tabview >=1.4 ; extra == 'full'
Provides-Extra: precommit
Requires-Dist: wilderness >=0.1.5 ; extra == 'precommit'
Provides-Extra: tests
Requires-Dist: wilderness >=0.1.5 ; extra == 'tests'
Requires-Dist: faust-cchardet >=2.1.18 ; extra == 'tests'
Requires-Dist: pandas >=1.0.0 ; extra == 'tests'
Requires-Dist: tabview >=1.4 ; extra == 'tests'
